<?xml version="1.0" encoding="utf-8"?>
<resources>
    <string name="abc_action_bar_home_description">Zur Startseite</string>
    <string name="abc_action_bar_up_description">Nach oben</string>
    <string name="abc_action_menu_overflow_description">Weitere Optionen</string>
    <string name="abc_action_mode_done">Fertig</string>
    <string name="abc_activity_chooser_view_see_all">Alle anzeigen</string>
    <string name="abc_activitychooserview_choose_application">App auswählen</string>
    <string name="abc_capital_off">AUS</string>
    <string name="abc_capital_on">AN</string>
    <string name="abc_menu_alt_shortcut_label">Alt +</string>
    <string name="abc_menu_ctrl_shortcut_label">Strg +</string>
    <string name="abc_menu_delete_shortcut_label">Löschen</string>
    <string name="abc_menu_enter_shortcut_label">Eingabetaste</string>
    <string name="abc_menu_function_shortcut_label">Funktionstaste +</string>
    <string name="abc_menu_meta_shortcut_label">Meta-Taste +</string>
    <string name="abc_menu_shift_shortcut_label">Umschalttaste +</string>
    <string name="abc_menu_space_shortcut_label">Leertaste</string>
    <string name="abc_menu_sym_shortcut_label">Sym-Taste +</string>
    <string name="abc_prepend_shortcut_label">Menütaste +</string>
    <string name="abc_search_hint">Suchen…</string>
    <string name="abc_searchview_description_clear">Suchanfrage löschen</string>
    <string name="abc_searchview_description_query">Suchanfrage</string>
    <string name="abc_searchview_description_search">Suche</string>
    <string name="abc_searchview_description_submit">Anfrage senden</string>
    <string name="abc_searchview_description_voice">Sprachsuche</string>
    <string name="abc_shareactionprovider_share_with">Teilen mit</string>
    <string name="abc_shareactionprovider_share_with_application">Mit %s teilen</string>
    <string name="abc_toolbar_collapse_description">Minimieren</string>
    <string name="about_us">Über uns</string>
    <string name="accept_email_push">Email Benachrichtigung</string>
    <string name="accept_msg_push">Benachrichtigungen einschalten</string>
    <string name="account_canceled">Konto gelöscht</string>
    <string name="add_device">Geräte hinzufügen</string>
    <string name="add_error">Hinzufügen fehlgeschlagen</string>
    <string name="address">Anschrift</string>
    <string name="after_sale">Kundendienst</string>
    <string name="aftersale_contact">Kontaktinformationen für den Kundendienst</string>
    <string name="aftersell_service">Kundendienst</string>
    <string name="age">Alter</string>
    <string name="agree">Einverstanden</string>
    <string name="alarm">Alarm</string>
    <string name="alarm_range">Alarmbereich</string>
    <string name="album">Fotos</string>
    <string name="all_choose">Alles auswählen</string>
    <string name="allread">Alle als gelesen markieren</string>
    <string name="amount">Betrag</string>
    <string name="answer_by_email">Wir werden Sie über Benachrichtigungen in der APP oder per E-Mail kontaktieren</string>
    <string name="app_name">robotic-mower connect</string>
    <string name="app_set">APP-Einstellungen</string>
    <string name="auto">Auto</string>
    <string name="auto_ota">Automatische Updates</string>
    <string name="auto_schedule">Automatischer Zeitplan</string>
    <string name="auto_schedule_tip">Im Bearbeitungsmodus müssen Sie nur die Startzeit einstellen und den Arbeitstag auswählen, die Maschine ordnet die Arbeitszeit automatisch nach Ihrem Gartenbereich und den Wetterbedingungen an.</string>
    <string name="auto_set">Auto</string>
    <string name="ava_device">Verfügbare Geräte</string>
    <string name="back">Rückkehr</string>
    <string name="back_to_order_manager">Zurück zur Bestellung</string>
    <string name="back_to_tracking_page">Zurückkehren</string>
    <string name="backhome">Rückkehr</string>
    <string name="battery">Akku:</string>
    <string name="battery2_too_high">Akku-Ladetemperatur zu hoch</string>
    <string name="battery2_too_low">Akku-Ladetemperatur zu niedrig</string>
    <string name="battery_comm_error">Akku-Kommunikationsfehler</string>
    <string name="battery_error">Akku nicht in Ordnung</string>
    <string name="battery_info">Batteriezustand</string>
    <string name="battery_low">Akku schwach, bitte zuerst aufladen</string>
    <string name="battery_too_high">Akku-Entladetemperatur zu hoch</string>
    <string name="battery_too_low">Akku-Entladetemperatur zu niedrig</string>
    <string name="beyond_scope">Außer Reichweite</string>
    <string name="bind_success_to_open_email_push">Verbindung erfolgreich, Benachrichtigungen einschalten?</string>
    <string name="bind_track_alerts_tip">Sie haben das Tracking-Modul nicht verbunden und können die Tracking-Funktion nicht nutzen. Bitte verbinden Sie das Tracking-Modul durch Scannen des QR-Codes</string>
    <string name="blade_block">Messermotor blockiert</string>
    <string name="ble_match">Bluetooth verbinden</string>
    <string name="ble_match_failed">Kopplung fehlgeschlagen</string>
    <string name="ble_matching">Bluetooth verbinden</string>
    <string name="bluetooth_connect">Bluetooth ist verbunden</string>
    <string name="bluetooth_disconnect">Bluetooth ist nicht verbunden</string>
    <string name="bluetooth_not_open">Bluetooth ist nicht eingeschaltet</string>
    <string name="border_line">Boundary</string>
    <string name="border_unconnect">Akku nicht verbunden</string>
    <string name="bottomsheet_action_expand_halfway">Zur Hälfte maximieren</string>
    <string name="boundary_error">Begrenzungsplatine nicht in Ordnung</string>
    <string name="brake_ble">Trennen</string>
    <string name="buy">Kaufen</string>
    <string name="can_use_time">Verfügbare Zeit</string>
    <string name="cancel">Abbrechen</string>
    <string name="cancel_account_tip">Sind Sie sicher, dass Sie Ihr Konto löschen möchten?</string>
    <string name="cancel_order">Bestellung stornieren</string>
    <string name="cancel_order_success">Bestellung erfolgreich storniert</string>
    <string name="cancel_refund">Rückerstattung stornieren</string>
    <string name="cancel_refund_success">Rückerstattung erfolgreich storniert</string>
    <string name="cancellation_of_accounts">Konto löschen</string>
    <string name="cao_zhong">Grasarten</string>
    <string name="certain_order">Bestellung bestätigen</string>
    <string name="certain_refund">Rückerstattung bestätigen</string>
    <string name="certain_to_pay">Bestätige Zahlung</string>
    <string name="character">Charakter</string>
    <string name="character_counter_content_description">Eingegebene Zeichen: %1$d von %2$d</string>
    <string name="character_counter_overflowed_content_description">Zeichenbeschränkung überschritten: %1$d/%2$d</string>
    <string name="charge_station">Ladestation</string>
    <string name="charging">Ladevorgang</string>
    <string name="charging_current_too_low">Ladestrom zu niedrig</string>
    <string name="charging_overtime">Laden dauert zu lange</string>
    <string name="check_new_version">Prüfen auf Update</string>
    <string name="chinese">Chinesisch</string>
    <string name="clear_text_end_icon_content_description">Text löschen</string>
    <string name="close">Schliessen</string>
    <string name="close_share_device">Stornieren</string>
    <string name="code_send_success">Bestätigungscode erfolgreich gesendet</string>
    <string name="code_time">senden(%1$sS)</string>
    <string name="com_facebook_device_auth_instructions">Gehe zu &lt;b&gt;facebook.com/device&lt;/b&gt; und gib den oben angezeigten Code ein.</string>
    <string name="com_facebook_image_download_unknown_error">Unerwarteter Fehler beim Herunterladen eines Bildes.</string>
    <string name="com_facebook_internet_permission_error_message">WebView-Anmeldung erfordert INTERNET-Berechtigung</string>
    <string name="com_facebook_internet_permission_error_title">AndroidOffensichtlicher Fehler</string>
    <string name="com_facebook_like_button_liked">Gefällt dir</string>
    <string name="com_facebook_like_button_not_liked">Gefällt mir</string>
    <string name="com_facebook_loading">Wird geladen ...</string>
    <string name="com_facebook_loginview_cancel_action">Abbrechen</string>
    <string name="com_facebook_loginview_log_in_button">Melde dich an</string>
    <string name="com_facebook_loginview_log_in_button_continue">Weiter mit Facebook</string>
    <string name="com_facebook_loginview_log_in_button_long">Mit Facebook anmelden</string>
    <string name="com_facebook_loginview_log_out_action">Abmelden</string>
    <string name="com_facebook_loginview_log_out_button">Abmelden</string>
    <string name="com_facebook_loginview_logged_in_as">Angemeldet als: %1$s</string>
    <string name="com_facebook_loginview_logged_in_using_facebook">Mit Facebook angemeldet</string>
    <string name="com_facebook_send_button_text">Senden</string>
    <string name="com_facebook_share_button_text">Teilen</string>
    <string name="com_facebook_smart_device_instructions">Öffne die Facebook-App auf deinem Mobilgerät, um dich mit deinem Konto zu verbinden und nach Benachrichtigungen zu suchen.</string>
    <string name="com_facebook_smart_device_instructions_or">- ODER -</string>
    <string name="com_facebook_smart_login_confirmation_cancel">Das bist du nicht?</string>
    <string name="com_facebook_smart_login_confirmation_continue_as">Weiter als %1$s</string>
    <string name="com_facebook_smart_login_confirmation_title">Anmeldung bestätigen</string>
    <string name="com_facebook_tooltip_default">Du bestimmst, welche Informationen du mit Apps teilen möchtest.</string>
    <string name="common_google_play_services_enable_button">Aktivieren</string>
    <string name="common_google_play_services_enable_text">%1$s funktioniert erst nach der Aktivierung der Google Play-Dienste.</string>
    <string name="common_google_play_services_enable_title">Google Play-Dienste aktivieren</string>
    <string name="common_google_play_services_install_button">Installieren</string>
    <string name="common_google_play_services_install_text">Zur Nutzung von %1$s sind die Google Play-Dienste erforderlich, die auf deinem Gerät nicht installiert sind.</string>
    <string name="common_google_play_services_install_title">Google Play-Dienste installieren</string>
    <string name="common_google_play_services_notification_channel_name">Verfügbarkeit von Google Play-Diensten</string>
    <string name="common_google_play_services_notification_ticker">Fehler bei Zugriff auf Google Play-Dienste</string>
    <string name="common_google_play_services_unknown_issue">%1$s hat Probleme mit Google Play-Diensten. Bitte versuche es noch einmal.</string>
    <string name="common_google_play_services_unsupported_text">Zur Nutzung von %1$s sind Google Play-Dienste erforderlich, die auf deinem Gerät nicht unterstützt werden.</string>
    <string name="common_google_play_services_update_button">Aktualisieren</string>
    <string name="common_google_play_services_update_text">%1$s wird nur ausgeführt, wenn du die Google Play-Dienste aktualisierst.</string>
    <string name="common_google_play_services_update_title">Google Play-Dienste aktualisieren</string>
    <string name="common_google_play_services_updating_text">Zur Nutzung von %1$s sind Google Play-Dienste erforderlich, die gerade aktualisiert werden.</string>
    <string name="common_google_play_services_wear_update_text">Eine neue Version der Google Play-Dienste wird benötigt. Diese wird in Kürze automatisch aktualisiert.</string>
    <string name="common_open_on_phone">Auf Smartphone öffnen</string>
    <string name="common_signin_button_text">Anmelden</string>
    <string name="common_signin_button_text_long">Über Google anmelden</string>
    <string name="config_wifi_hint">Konfigurieren Sie WLAN und Sie können Ihre Geräte von überall aus steuern.</string>
    <string name="confirm">Bestätigen</string>
    <string name="confirm_cancel_tip">Bitte bestätigen Sie vor dem Löschen</string>
    <string name="connect">Verbinden</string>
    <string name="connect_ble">Bluetooth wird verbunden</string>
    <string name="connect_failed">Verbindung fehlgeschlagen</string>
    <string name="connect_wifi_tip">Bitte geben Sie SSID und Passwort für das WLAN ein und klicken Sie auf «Connect» (Verbinden), um die Konfiguration des Netzwerks zu starten. Tipps: Nur mit 2,4 GHz-Netzwerken kompatibel</string>
    <string name="connect_wifi_to_update">Bitte verbinden Sie sich mit WLAN, um ein Upgrade durchzuführen</string>
    <string name="contact">Kontaktinformationen</string>
    <string name="contact_star">*Email</string>
    <string name="continue_pay">Weiter</string>
    <string name="copyright">Copyright © 2014 - SUNSEEKER - All rights reserved.</string>
    <string name="country_region">Land / Region</string>
    <string name="current_version">Aktuelle Version</string>
    <string name="cutting_area">Schnittbereich</string>
    <string name="cutting_length">Länge</string>
    <string name="czech">Tschechisch</string>
    <string name="danish">dänisch</string>
    <string name="day">Tag</string>
    <string name="day_light_time">Auf Sommerzeit umstellen</string>
    <string name="day_one">Tag</string>
    <string name="day_time">Tage</string>
    <string name="deadline_date">Gültig bis:</string>
    <string name="delation_cleared">Nach dem Löschen wird der gesamte Geräteverlauf gelöscht</string>
    <string name="delation_device_unbound">Nach dem Löschen wird das Gerät automatisch von diesem Konto entfernt</string>
    <string name="delation_device_unbound_detail">Nach dem Löschen können Sie sich nicht mehr mit Ihrem Konto anmelden und freigegebene Geräte werden automatisch entfernt.</string>
    <string name="delay">Verzögerung</string>
    <string name="delete">Löschen</string>
    <string name="delete_failed">Löschen fehlgeschlagen</string>
    <string name="delete_success">Erfolgreich gelöscht</string>
    <string name="delete_work_map_fail">Karte konnte nicht gelöscht werden</string>
    <string name="delete_work_map_success">Karte erfolgreich gelöscht</string>
    <string name="delete_work_map_title">Möchten Sie die aktuelle Karte wirklich löschen?</string>
    <string name="deteing_information">Nach dem Löschen werden das Geräteprotokoll und alle Ihre Geräteinformationen dauerhaft entfernt</string>
    <string name="device_add_success">Gerät erfolgreich hinzugefügt</string>
    <string name="device_back">Der Roboter kehrt zur Ladestation zurück</string>
    <string name="device_battery">Roboter lädt auf</string>
    <string name="device_bounded">Gerät ist bereits verbunden</string>
    <string name="device_close">Roboter ausgeschaltet</string>
    <string name="device_cut_area">Gesamte Mäherfläche</string>
    <string name="device_delete">Gerät löschen</string>
    <string name="device_error">Roboter hat eine Fehlermeldung</string>
    <string name="device_error_notification">Push-Benachrichtigung – Gerätefehler</string>
    <string name="device_error_push">Fehlermeldung</string>
    <string name="device_help_tips">Wenn sich der Mähroboter festgefahren hat bzw. feststeckt, muss er von Hand wieder in Position gebracht und gestartet werden</string>
    <string name="device_list">Geräte</string>
    <string name="device_log">Geräteprotokolle</string>
    <string name="device_name">Gerätenamen</string>
    <string name="device_not_connect">Gerät nicht verbunden</string>
    <string name="device_offline">Offline</string>
    <string name="device_online">Online</string>
    <string name="device_open">Roboter eingeschaltet</string>
    <string name="device_param">Geräteparameter</string>
    <string name="device_params">Geräteparameter</string>
    <string name="device_rain_back">Regen erkannt, Roboter kehrt zur Ladestation zurück</string>
    <string name="device_run_time">Gesamtlaufzeit</string>
    <string name="device_sn">Seriennummer</string>
    <string name="device_standby">Der Roboter befindet sich im Standby-Modus</string>
    <string name="device_stop_share">Das Gerät wurde nicht mehr geteilt</string>
    <string name="device_to_unbind">Gerät entfernen</string>
    <string name="device_tracking">Verfolgung</string>
    <string name="device_unbind">Das Gerät wurde aus dem Konto entfernt</string>
    <string name="device_work">Roboter beginnt zu arbeiten</string>
    <string name="disagree">Nicht einverstanden</string>
    <string name="disconnect_bluetooth">Bluetooth auf \"%1$s\" trennen</string>
    <string name="display_error">Displayplatine nicht in Ordnung</string>
    <string name="do_not_have_work_map">Derzeit keine Karte</string>
    <string name="dock_toomany_failed">Andocken zu oft fehlgeschlagen</string>
    <string name="dutch">Niederländisch</string>
    <string name="e_mail">E-mail</string>
    <string name="edge">Kante</string>
    <string name="edit">Bearbeiten</string>
    <string name="edit_help_tips">Klicken Sie hier, um den Zeitplan zu bearbeiten. Speichern Sie den Zeitplan nach der Bearbeitung</string>
    <string name="eg_useragreement">Bevor Sie unsere Produkte und Dienstleistungen nutzen, lesen Sie bitte die Nutzungsvereinbarung und die Datenschutzerklärung sorgfältig durch. Um sicherzustellen, dass Sie unsere Produkte normal nutzen können, bitten wir Sie um Erteilung der folgenden Berechtigungen: 1. Netzwerk-Berechtigung 2. Foto-Berechtigung 3. Kamera-Berechtigung 4. Standort-Berechtigung 5. Benachrichtigungs-Berechtigung 6. Bluetooth-Berechtigung. Wenn Sie mit der Nutzungsvereinbarung und der Datenschutzerklärung einverstanden sind, klicken Sie auf die Schaltfläche «Einverstanden», um die Nutzung der hochwertigen Dienstleistungen unseres Unternehmens zu beginnen.</string>
    <string name="electronic_fence">Geofence-Einstellungen</string>
    <string name="electronic_fencing">Digitaler Zaun</string>
    <string name="electronic_tip">Nach der Installation und Bindung des Tracking-Moduls können Sie den aktuellen Standort des Roboters anzeigen und den Geo-Zaun festlegen.</string>
    <string name="email">E-mail</string>
    <string name="email_error">Sie haben eine ungültige E-Mail-Adresse eingegeben. Bitte versuchen Sie es erneut.</string>
    <string name="email_notification">Email Benachrichtigung</string>
    <string name="email_push_tip">Wenn eingeschaltet, werden Sie benachrichtigt, wenn sich das Gerät außerhalb der Reichweite befindet.</string>
    <string name="email_setting">Email Einstellungen</string>
    <string name="end_time_one">Endzeit eins</string>
    <string name="end_time_two">Endzeit zwei</string>
    <string name="english">Englisch</string>
    <string name="enter_confirm_pwd">Bitte bestätigen Sie das Passwort.</string>
    <string name="enter_old_pwd">Bitte altes Passwort eingeben</string>
    <string name="enter_pwd">Bitte geben Sie das Passwort ein.</string>
    <string name="error">Fehler</string>
    <string name="error0x01">Fehler: Maschine wird umgedreht, bitte stellen Sie sicher, dass die Maschine richtig platziert ist</string>
    <string name="error0x02">Fehler: Zu viele Hindernisse erkannt, bitte stellen Sie die Maschine an einen neuen Ort</string>
    <string name="error0x03">Fehler: Maximale Fläche überschritten</string>
    <string name="error0x04">Fehler: Die Maschine wird angehoben, bitte bringen Sie die Maschine an einen ebenen Platz</string>
    <string name="error0x08">Fehler: Zu oft konnte keine Verbindung zur Ladestation hergestellt werden. Bitte prüfen Sie, ob es viele Hindernisse rund um die Ladestation</string>
    <string name="error0x10">Fehler: Kein Grenzsignal, bitte prüfen Sie, ob die Ladestation eingeschaltet und die Grenzlinie unterbrochen ist</string>
    <string name="error0x100">Fehler: Die Batterietemperatur ist zu niedrig, bitte warten Sie, bis die Temperatur der Batterie aufgewärmt ist</string>
    <string name="error0x1000">Fehler: Systemfehler, bitte starten Sie das Gerät neu</string>
    <string name="error0x10000">Fehler: Ladestrom zu groß, bitte Service kontaktieren</string>
    <string name="error0x100000">Fehler: Der Schneidmotor ist blockiert, bitte prüfen Sie den Schneidkopf</string>
    <string name="error0x1000000">Fehler: Die Batterietemperatur ist zu niedrig, bitte warten Sie, bis die Temperatur der Batterie aufgewärmt ist</string>
    <string name="error0x20">Fehler: Die Maschine wird außerhalb der Begrenzungslinie gestartet, bitte bringen Sie die Maschine innerhalb der Begrenzungslinie und prüfen Sie, ob die Begrenzungslinie an der Ladestation richtig angeschlossen ist</string>
    <string name="error0x200">Fehler: Die Batteriespannung ist anormal, bitte versuchen Sie die Batterie aufzuladen</string>
    <string name="error0x2000">Fehler: Ladestrom zu groß, bitte Service kontaktieren</string>
    <string name="error0x20000">Fehler: Die Batteriespannung ist anormal, bitte Batterie wechseln</string>
    <string name="error0x200000">Fehler: Der Neigungswinkel ist zu groß</string>
    <string name="error0x2000000">Fehler: Die Batterietemperatur ist zu niedrig, bitte warten Sie, bis die Temperatur der Batterie aufgewärmt ist</string>
    <string name="error0x40">Fehler: Die schwimmende Abdeckung löst den Kollisionssensor zu oft aus.</string>
    <string name="error0x400">Fehler: Die Batteriespannung ist anormal, bitte versuchen Sie die Batterie aufzuladen</string>
    <string name="error0x4000">Fehler: Die Batteriespannung ist anormal, bitte Batterie wechseln</string>
    <string name="error0x40000">Fehler: Ladestrom zu groß, bitte Service kontaktieren</string>
    <string name="error0x400000">Fehler: Systemfehler, bitte starten Sie das Gerät neu</string>
    <string name="error0x4000000">Fehler: Systemfehler, bitte starten Sie das Gerät neu</string>
    <string name="error0x4fffffff">Fehler: Systemfehler, bitte starten Sie das Gerät neu</string>
    <string name="error0x80">Fehler: Die Batterietemperatur ist zu niedrig, bitte warten Sie, bis die Temperatur der Batterie aufgewärmt ist</string>
    <string name="error0x8000">Fehler: Systemfehler, bitte starten Sie das Gerät neu</string>
    <string name="error0x80000">Fehler: Der Antriebsmotor ist blockiert, bitte prüfen Sie die Hinterräder</string>
    <string name="error0x800000">Fehler: Systemfehler, bitte starten Sie das Gerät neu</string>
    <string name="error0x8000000">Fehler: Systemfehler, bitte starten Sie das Gerät neu</string>
    <string name="error_code">Fehlercode:</string>
    <string name="error_icon_content_description">Fehler</string>
    <string name="exit">Abmelden</string>
    <string name="exposed_dropdown_menu_content_description">Drop-down-Menü anzeigen</string>
    <string name="fail_reason">Grund für Zahlungsausfall</string>
    <string name="faq">FAQ</string>
    <string name="far">Weit</string>
    <string name="feedback_hint_star">Feedback-Inhalt</string>
    <string name="feedback_question_push">Feedback-Benachrichtigung</string>
    <string name="feedback_success">Erfolgreich übermittelt</string>
    <string name="finish_info">Benutzerinformationen ergänzen</string>
    <string name="finish_info2">Bitte füllen Sie die Benutzerinformationen aus</string>
    <string name="finish_time">Bezahlt am</string>
    <string name="finnish">finnisch</string>
    <string name="forget_pwd">Passwort vergessen</string>
    <string name="france">Französisch</string>
    <string name="friday">Fr.</string>
    <string name="from_album">Fotos aus dem Album auswählen</string>
    <string name="fujian">Anhang</string>
    <string name="gear">Abstand der Hinderniserkennung</string>
    <string name="german">Deutsch</string>
    <string name="good">Gut</string>
    <string name="graden_area">Gartenbereich</string>
    <string name="hardware_module_error">Hardwaremodulfehler</string>
    <string name="has_new_version">Neue Version verfügbar</string>
    <string name="head">Profilbild</string>
    <string name="head_light_open">Einschalten</string>
    <string name="head_light_tip">Die Scheinwerfer können ein-/ausgeschaltet werden. Sie können einstellen, ob weißes Licht verwendet werden soll</string>
    <string name="hebrew">Hebräisch</string>
    <string name="help_center">Hilfe-Center</string>
    <string name="help_center_tip">Anleitung und Service</string>
    <string name="help_hint">Bitte prüfen Sie, ob der Roboter eingeschaltet ist, ob Bluetooth bei Ihrem Handy aktiviert ist, ob das WLAN-Signal vorhanden ist.</string>
    <string name="hint_forget_pwd">Passwort vergessen</string>
    <string name="hint_input_code">Bestätigungscode</string>
    <string name="hint_input_email">Bitte geben Sie Ihre E-Mail-Adresse ein.</string>
    <string name="hint_login">Haben Sie bereits ein Konto? Hier anmelden</string>
    <string name="hint_nodevice">Noch keine Geräte, bitte hinzufügen</string>
    <string name="hint_register">Sie haben noch kein Konto? Registrieren</string>
    <string name="hint_useragreement">Nutzungsvereinbarung/Datenschutzerklärung</string>
    <string name="home">Home</string>
    <string name="home_help_tips">Wenn Sie möchten, dass das Gerät wieder aufgeladen wird, müssen Sie zuerst die STOP-Taste drücken, um die aktuelle Arbeit des Robotes zu stoppen</string>
    <string name="hour">Stunde</string>
    <string name="hungarian">ungarisch</string>
    <string name="icon_content_description">Dialogfeldsymbol</string>
    <string name="idle">Standby</string>
    <string name="in_backing">Rückkehr</string>
    <string name="in_charging">Ladevorgang</string>
    <string name="in_stoping">Standby</string>
    <string name="in_working">Betrieb</string>
    <string name="info">Information</string>
    <string name="info_fix">Benutzerinformationen ergänzen</string>
    <string name="input_pwd">Passwort eingeben</string>
    <string name="is_update_now">Jetzt aktualisieren?</string>
    <string name="italy">Italienisch</string>
    <string name="item_view_role_description">Tab</string>
    <string name="japanese">japanisch</string>
    <string name="job">Beruf</string>
    <string name="jump">Überspringen</string>
    <string name="language">Sprache</string>
    <string name="later">Später</string>
    <string name="law_info">Rechtliche Hinweise</string>
    <string name="led_setting">Scheinwerfereinstellung</string>
    <string name="lift_up">Hochhebe</string>
    <string name="link_success">Verbindung erfolgreich</string>
    <string name="loading">Wird geladen</string>
    <string name="login">Anmelden</string>
    <string name="login_error">Benutzername oder Passwort falsch</string>
    <string name="login_fail">Anmeldung fehlgeschlagen, bitte versuchen Sie es erneut oder melden Sie sich mit anderer Methode an</string>
    <string name="login_toast_check_agree">Bitte setzen Sie ein Häkchen und stimmen Sie den Nutzungsbedingungen|Datenschutzbestimmungen zu</string>
    <string name="logout_tip">Sind Sie sicher, dass Sie sich abmelden wollen?</string>
    <string name="machine_pwd">Das Passwort des Rasenmähroboters</string>
    <string name="machine_pwd_error">Registrierung erfolgreich</string>
    <string name="man">Männlich</string>
    <string name="manual_connect">Manuelle Verbindung</string>
    <string name="manual_connect_ble">über Bluetooth verbinden</string>
    <string name="map">Karte</string>
    <string name="material_clock_toggle_content_description">Vormittags oder Nachmittags auswählen</string>
    <string name="material_hour_selection">Stunde auswählen</string>
    <string name="material_hour_suffix">%1$s Uhr</string>
    <string name="material_minute_selection">Minuten auswählen</string>
    <string name="material_minute_suffix">%1$s Minuten</string>
    <string name="material_timepicker_am">AM</string>
    <string name="material_timepicker_clock_mode_description">In den Uhrzeitmodus wechseln, um die Uhrzeit einzugeben.</string>
    <string name="material_timepicker_hour">Stunde</string>
    <string name="material_timepicker_minute">Minute</string>
    <string name="material_timepicker_pm">PM</string>
    <string name="material_timepicker_select_time">Uhrzeit auswählen</string>
    <string name="material_timepicker_text_input_mode_description">In den Texteingabemodus wechseln, um die Uhrzeit einzugeben.</string>
    <string name="medium">Mitte</string>
    <string name="min">Minute</string>
    <string name="mode_status">Modulstatus</string>
    <string name="model">Modell</string>
    <string name="modify_device_name">Gerätenamen ändern</string>
    <string name="modify_failed">Änderung fehlgeschlagen</string>
    <string name="modify_success">Erfolgreich geändert</string>
    <string name="monday">Mo.</string>
    <string name="month">Monat</string>
    <string name="msg_detail">Nachrichteninhalt</string>
    <string name="msg_manage">Nachrichten</string>
    <string name="msg_notification">Push-Benachrichtigung – Nachricht</string>
    <string name="mtrl_badge_numberless_content_description">Neue Benachrichtigung</string>
    <string name="mtrl_chip_close_icon_content_description">%1$s entfernen</string>
    <string name="mtrl_exceed_max_badge_number_content_description">Mehr als %1$d neue Benachrichtigungen</string>
    <string name="mtrl_picker_a11y_next_month">Zum nächsten Monat wechseln</string>
    <string name="mtrl_picker_a11y_prev_month">Zum vorherigen Monat wechseln</string>
    <string name="mtrl_picker_announce_current_selection">Aktuelle Auswahl: %1$s</string>
    <string name="mtrl_picker_confirm">@android:string/ok</string>
    <string name="mtrl_picker_date_header_selected">%1$s</string>
    <string name="mtrl_picker_date_header_title">Datum auswählen</string>
    <string name="mtrl_picker_date_header_unselected">Ausgewähltes Datum</string>
    <string name="mtrl_picker_day_of_week_column_header">Spalte \"Wochentag\": %1$s</string>
    <string name="mtrl_picker_invalid_format">Ungültiges Format.</string>
    <string name="mtrl_picker_invalid_format_example">Beispiel: %1$s</string>
    <string name="mtrl_picker_invalid_format_use">Format: %1$s</string>
    <string name="mtrl_picker_invalid_range">Ungültiger Bereich.</string>
    <string name="mtrl_picker_navigate_to_year_description">Zum Jahr %1$s wechseln</string>
    <string name="mtrl_picker_out_of_range">Außerhalb des Bereichs: %1$s</string>
    <string name="mtrl_picker_range_header_only_end_selected">Startdatum – %1$s</string>
    <string name="mtrl_picker_range_header_only_start_selected">%1$s – Enddatum</string>
    <string name="mtrl_picker_range_header_selected">%1$s – %2$s</string>
    <string name="mtrl_picker_range_header_title">Zeitraum auswählen</string>
    <string name="mtrl_picker_range_header_unselected">Startdatum – Enddatum</string>
    <string name="mtrl_picker_save">Speichern</string>
    <string name="mtrl_picker_text_input_date_hint">Datum</string>
    <string name="mtrl_picker_text_input_date_range_end_hint">Enddatum</string>
    <string name="mtrl_picker_text_input_date_range_start_hint">Startdatum</string>
    <string name="mtrl_picker_text_input_day_abbr">T</string>
    <string name="mtrl_picker_text_input_month_abbr">M</string>
    <string name="mtrl_picker_text_input_year_abbr">J</string>
    <string name="mtrl_picker_toggle_to_calendar_input_mode">In den Kalendereingabemodus wechseln</string>
    <string name="mtrl_picker_toggle_to_day_selection">Tippen, um zur Tagesauswahl zu wechseln</string>
    <string name="mtrl_picker_toggle_to_text_input_mode">In den Texteingabemodus wechseln</string>
    <string name="mtrl_picker_toggle_to_year_selection">Tippen, um zur Jahresauswahl zu wechseln</string>
    <string name="multi_arrive_percent">Häufigkeit</string>
    <string name="multi_arrive_percent_no_0">Die Häufigkeit kann nicht alle 0 Prozent betragen.</string>
    <string name="multi_pop_meter">Meter</string>
    <string name="multi_pop_percent">Prozent</string>
    <string name="multi_set_error">Einrichtung fehlgeschlagen</string>
    <string name="multi_set_success">Erfolgreich eingestellt</string>
    <string name="multiarea">Startpunkt</string>
    <string name="munal">Manuell</string>
    <string name="name">Name</string>
    <string name="name_length_too_long">Gerätename zu lang</string>
    <string name="near">Nah</string>
    <string name="need_new_battery">Akku muss ausgetauscht werden</string>
    <string name="net_error">Netzwerkfehler</string>
    <string name="new_data_have_not_save">Zeitplan wurde nicht gespeichert, möchten Sie speichern?</string>
    <string name="next_step">Weiter</string>
    <string name="no_border">Keine Begrenzung</string>
    <string name="no_current_device_map">Das aktuelle Gerät hat keine Karte</string>
    <string name="no_led">Keine LED-Funktion</string>
    <string name="no_longer_avaliable">Dieser Plan ist nicht mehr verfügbar</string>
    <string name="no_multi_area">Das Gerät kann keinen Startpunkt setzen</string>
    <string name="no_net_work">keine Netzwerkverbindung</string>
    <string name="no_rain_set">Das Gerät verfügt nicht über eine Regenverzögerungs-Funktion</string>
    <string name="no_schedule_tip">Der aktuelle Zeitplan ist leer, das Gerät wird nicht automatisch arbeiten.</string>
    <string name="no_ultra">Keine Ultraschallfunktion</string>
    <string name="no_valid_content">Kein gültiger Inhalt erkannt</string>
    <string name="no_work_map_tip">(Karte wird während der Arbeit generiert und optimiert)</string>
    <string name="no_work_schedule">Das Gerät verfügt nicht über eine Zeitplanfunktion</string>
    <string name="nomore_six">maximal 6 Bilder</string>
    <string name="norwegian">norwegisch</string>
    <string name="nosignal_one">Kein Signal von einem Begrenzungssensor</string>
    <string name="open">Einschalten</string>
    <string name="open_gps_for_wifilist">Bitte schalten Sie GPS ein, um die WLAN-Liste zu erhalten</string>
    <string name="or">oder</string>
    <string name="order_cancel_time">Auftragsstornierungszeit</string>
    <string name="order_create_time">Erstellungszeit der Bestellung</string>
    <string name="order_expiration_time">Ablaufzeit der Bestellung</string>
    <string name="order_manager">Bestellung</string>
    <string name="order_num">Bestellnummer</string>
    <string name="order_pay_time">Zahlungszeit</string>
    <string name="order_state">Bestellstatus：</string>
    <string name="ota_newest">Keine Aktualisierung verfügbar</string>
    <string name="ota_query_failed">Update prüfen fehlgeschlagen</string>
    <string name="ota_send_fail_retry">Der Firmware-Download ist fehlgeschlagen. Stellen Sie beim Herstellen einer WLAN-Verbindung für ein Upgrade sicher, dass sich das Netzwerk in einem guten Zustand befindet</string>
    <string name="ota_send_not_back">Die Firmware wird heruntergeladen, bitte verlassen Sie die App nicht</string>
    <string name="ota_send_success_wait">Der Firmware-Download ist erfolgreich. Warten Sie, bis der Roboter das Upgrade abgeschlossen hat. Schalten Sie den Roboter nicht aus, wenn Load angezeigt wird</string>
    <string name="ota_send_wait">Firmware herunterladen, bitte warten</string>
    <string name="ota_update">Upgrade durchführen</string>
    <string name="ota_update_failed">Update fehlgeschlagen</string>
    <string name="ota_update_success">Aktualisierung erfolgreich</string>
    <string name="ota_upgrade">Firmware Update</string>
    <string name="other_error">Sonstiger Fehler</string>
    <string name="outofarea">Ausserhalb der Begrenzung</string>
    <string name="over_dl">Überstrom beim Laden</string>
    <string name="overlage">Überspannung beim Laden</string>
    <string name="overtime_dl">Erhaltungsladung dauert zu lange</string>
    <string name="package_detail">Tarif Beschreibung</string>
    <string name="package_left_time">Restzeit</string>
    <string name="package_time_length">Tarif-Zeitdauer</string>
    <string name="package_time_select">Tarif wählen</string>
    <string name="pai_help_tips">Klicken Sie irgendwo in das leere Feld oder ziehen Sie, um den Zeitplan festzulegen. Der Mäher arbeitet innerhalb des Zeitplans und kehrt nach Ablauf des Zeitplans automatisch zur Ladestation zurück.</string>
    <string name="password_toggle_content_description">Passwort anzeigen</string>
    <string name="pause">Pause</string>
    <string name="pause_schedule">Terminplanung pausiert</string>
    <string name="pause_schedule_normal_work">Während der Planung arbeitet die Maschine normal</string>
    <string name="pause_schedule_pause_work">Während der Planung pausiert die Maschine ihre Arbeit</string>
    <string name="pay_fail">Bezahlung fehlgeschlagen</string>
    <string name="pay_result">Zahlungsergebnis</string>
    <string name="pay_success">Bezahlung erfolgreich</string>
    <string name="pay_wait">Ausstehende Zahlung</string>
    <string name="pending_wait_tip">Paypal bearbeitet diese Bestellung, bitte warten</string>
    <string name="pick_photo_video">Video/bilder hochladen</string>
    <string name="pickpic">Bild auswählen</string>
    <string name="pickvideo">Videos auswählen</string>
    <string name="please_connect_ble">Bitte Bluetooth verbinden</string>
    <string name="please_enter_address">Bitte füllen Sie die Adresse aus</string>
    <string name="please_enter_age">Bitte geben Sie Ihr alter ein</string>
    <string name="please_enter_area">Bitte füllen Sie den Bereich aus</string>
    <string name="please_enter_email">Bitte füllen Sie die E-Mail-Adresse aus</string>
    <string name="please_enter_pwd">Bitte geben Sie Ihr Kontopasswort ein</string>
    <string name="please_enter_wifi_name">Bitte WLAN-Namen eingeben</string>
    <string name="please_fill_in_your_name">Bitte tragen Sie Ihren Namen ein</string>
    <string name="please_input">Bitte eingeben</string>
    <string name="please_input_content">Bitte Feedback-Inhalt eingeben</string>
    <string name="please_input_device_name">Gerätenamen oder SN eingeben</string>
    <string name="please_input_device_password">Bitte geben Sie zuerst das Gerätepasswort ein</string>
    <string name="please_input_email">Geben Sie bitte Ihre Email-Adresse ein</string>
    <string name="please_open_ble">Bitte Bluetooth einschalten</string>
    <string name="please_select">bitte auswählen</string>
    <string name="please_select_country_area">Bitte Land auswählen</string>
    <string name="please_select_grass">Bitte wählen Sie den Grassamen aus</string>
    <string name="please_select_sex">Bitte wählen Sie Geschlecht</string>
    <string name="please_select_work">Bitte wählen Sie Ihren Beruf aus</string>
    <string name="please_select_work_day">Wochentag auswählen</string>
    <string name="please_set_schedule_time">Bitte Zeitplan einstellen</string>
    <string name="please_write_refund_reason">Bitte geben Sie den Grund für die Rückerstattung ein</string>
    <string name="policy_content">\t\t\t\tThe copyright of robotic lawn mower APP (referred to as this product) belongs to SHANGHAI SUNSEEKER ROBOTIC TECHNOLOGY CO.,LTD. (hereinafter referred to as “SUNSEEKER ROBOTIC”). This product provided by  SUNSEEKER ROBOTIC  is a mobile service application software product based on robotic lawn mower, which provides customers with information services such as remote control of robotic lawn mower and after-sales feedback. In accordance with the provisions of the law, we will collect, use, save or disclose your personal information under certain circumstances. If you have any questions about this Privacy Policy or matters regarding this Privacy Policy, please contact Harry@sunseekerpower.cn. \n\n\t\t\t\tThis Privacy Statement is closely related to the products and services of this application you use, we recommend that you read this Privacy Notice in full to ensure you are fully informed and make the appropriate choice you think in accordance with the guidelines of the Privacy Policy. \n\n\t\t\t\t1、Collection of personal information \n\n \t\t\t\t1.1 Personal information \n\n\t\t\t\tWe use, save or disclose personal information to provide you with services through account creation, email notification, message notification, etc.  SUNSEEKER ROBOTIC  will provide you with a series of services such as equipment control, equipment scheduling, equipment settings, message management, etc. \n\n\t\t\t\tThis product guarantees that it will not collect information prohibited by laws and regulations. What we collect: \n\n\t\t\t\t1.1.1 When you register as a member, the email account and third-party account information provided are used to help you automatically extract information such as changes to the account binding or managed smart devices. \n\n\t\t\t\t1.1.2 When you browse or use  SUNSEEKER ROBOTIC  products or service initiative to provide us with information to help you quickly handle after-sales service and device detail information management. We can through these information, evaluating the service quality, optimize the user experience, portraits and user preferences for your behavior and so on, to provide you with more personality and convenient services. \n\n\t\t\t\t1.1.3 Relevant information recorded in the process of providing you with services, so that you can check the device’s status or relevant after-sales service progress, etc. \n\n\t\t\t\t1.1.4 When providing you with after-sales instructions and other services, in order to have a better service, we will collect your location information and device’s status, so that we could provide you with more complete and faster services. \n\n\t\t\t\t1.1.5 The information you initiatively submit or feedback through our customer service staff or other channels, so that we can understand and evaluate the quality of services and optimize the user experience. \n\n\t\t\t\t1.1.6 Collect and store legally obtained information about you from a third-party independent data source. \n\n\t\t\t\t1.1.7 The information you provide,  SUNSEEKER ROBOTIC  will maximize the reasonable business obligations to keep confidential. With your consent,  SUNSEEKER ROBOTIC  will provide you with services such as the information of device’s after-sales service and version upgrades. \n\n\t\t\t\t1.2 Your other information \n\n\t\t\t\tIn order to make it more convenient for you to use this product and improve the security of your use of our services, our server will collect Mac information about your lawn mower device, Bluetooth information that can be obtained by mobile terminals, device location information, third-party account user\'s name, profile picture and other similar characteristics records. \n\n\t\t\t\t2、Use and sharing of personal information \n\n\t\t\t\t2.1 Your personal information will not be used for other purposes unless it is stated in this Privacy Policy or after notifying you that we update our Privacy Policy. \n\n\t\t\t\t2.3 You can view your personal information in My Account from the mobile APP at any time or get device status information on device list, device control page and other interfaces. We will take privacy treatment of your personal information such as the Email address, device’s password etc. in “My Account”, to avoid information leakage and loss caused by improper use of your device. \n\n\t\t\t\t2.4 The server of  SUNSEEKER ROBOTIC  is located in Amazon, your information will be stored in Amazon Web Services and processed in Amazon in accordance with the User Agreement or with the Privacy Policy. \n\n\t\t\t\t2.5 During your use of  SUNSEEKER ROBOTIC  products or services, we will keep your information until you cancel your account or make a deletion request. After you cancel your account or make a deletion request, we will delete or anonymize your information. \n\n\t\t\t\t2.6  SUNSEEKER ROBOTIC  will not sell any customer information or share your information with third parties without your permission unless it is stated in this Privacy Policy. You are fully aware that in the following circumstances, we do not need your authorization to collect and use personal information. \n\n\t\t\t\t2.6.1 According to applicable laws and regulations, legal procedures or mandatory government requirements or judicial rulings. \n\n\t\t\t\t2.6.2 Related to national security and national defense security. \n\n\t\t\t\t2.6.3 When permitted by laws and regulations, in order to protect  SUNSEEKER ROBOTIC  from infringement of its own interests. \n\n\t\t\t\t2.6.4 In order to protect the personal information or other personal life, property and other major legal rights, but it is difficult to obtain the consent of the person. \n\n\t\t\t\t2.6.5 The personal information collected is disclosed to the public by the subject of personal information. \n\n\t\t\t\t2.6.6 Collect your personal information from legally publicly disclosed information, such as legal news reports, government information disclosure and other channels. \n\n\t\t\t\t2.6.7 Necessary for signing a contract according to your requirements. \n\n\t\t\t\t2.6.8 Necessary for maintaining the safe and stable operation of the products and services, such as product detecting, product handling and service failures. \n\n\t\t\t\tOther circumstances stipulated by laws and regulations. \n\n\t\t\t\t3、Disclosure of personal information \n\n\t\t\t\t3.1 Unless the limited disclosure stated in this privacy statement, we will properly keep your personal information and will not disclose the list of customers \n\n\t\t\t\t3.2 You hereby authorize that, in the following circumstances, we will disclose your personal information to a third party without your consent. \n\n\t\t\t\t3.2.1 If we disclose this information to identify, contact or file a lawsuit that may cause damage to our rights or property, website users or anyone else (including the rights and property of any other person). \n\n\t\t\t\t3.2.2 The need for legal investigation \n\n\t\t\t\tSuch disclosure is necessary for subpoenas or other warrants issued by law enforcement agencies that are required by law or should be served on us \n\n\t\t\t\t4、Special reminder for sensitive personal information \n\n\t\t\t\tYour special personal information, such as your personal phone number, email address, and location information are considered personal sensitive information. Before collecting such personal sensitive information, you need to consider carefully. At the same time,  SUNSEEKER ROBOTIC  will obtain your consent and strictly protect your sensitive personal information. If you do not provide this information or the information provided is incorrect, it may cause us to be unable to provide services or affect the accuracy of the information we provide. \n\n\t\t\t\t5、 Security \n\n\t\t\t\t5.1 For us, the security of personal information is very important. We will make reasonable commercial efforts to ensure the security of your personal information, and implement reasonable business procedures to restrict unauthorized access, use or disclosure of your personal information. All data storage involving personal information uses multiple encryptions. We will not keep your personal information for longer than necessary for processing purposes and will keep it for as long as necessary for the purpose for which it was collected in accordance with our data retention policy. Despite taking the above measures, you should be aware that  SUNSEEKER ROBOTIC  cannot completely avoid the safety hazards related to personal information. \n\n\t\t\t\t5.2 Please understand that due to technical limitations or various malicious methods that may exist, in the Internet industry, even if you do your best to strengthen security measures, it is impossible to always guarantee 100% security of information. You need to understand that the system or communication network you use to access the services of this application may have problems due to factors outside the controllable range of this application. \n\n\t\t\t\t5.3  SUNSEEKER ROBOTIC  attaches great importance to the safety of personal information and your data. Comply with all relevant data security regulations. If there is a risk of personal information leakage or damage,  SUNSEEKER ROBOTIC  will notify you in time through push notifications so that you can avoid losses as soon as possible. At the same time, report to the regulatory agency within 72 hours after the leaked data. If you find that your personal information is leaked, please contact our customer service immediately so that we can take corresponding measures. \n\n\t\t\t\tYou should assist us to protect the security of your personal information. For example, please do not arbitrarily leak or share the QR code of authorized devices on social media. \n\n\t\t\t\t7、Amendments to this Privacy Policy \n\n\t\t\t\t7.1 This Privacy Policy allows adjustments. If we make any substantial adjustments to the method of using your personal information, we will notify you through a message and announce the revision date so that you can know when the Privacy Policy was last updated. When you use this product, you can review our Privacy Policy at any time. \n\n\t\t\t\t7.2 The messages we send that contain such change notices undoubtedly constitute an effective part of the above change notices. If you do not want us to change the use of your personal information, you must notify us before you expect to stop using our account. Your continued use of this product will be deemed to be that you know and agree to be bound by such changes in the notice. \n\n\t\t\t\tThe establishment, entry into force, performance, interpretation and dispute resolution of this statement are governed by the laws of the mainland of the People\'s Republic of China (excluding conflict of laws). If any of these terms conflict with the laws of the People\'s Republic of China, these terms will be completely reinterpreted in accordance with the law, while other terms still have legal effect. Disputes between you and  SUNSEEKER ROBOTIC  on this statement or other related matters should first be settled through friendly negotiation. If the negotiation fails, the dispute or dispute should be brought to the jurisdiction of the court with jurisdiction where SHANGHAI SUNSEEKER ROBOTIC TECHNOLOGY CO.,LTD. is located.</string>
    <string name="polish">Polieren</string>
    <string name="portuguese">Portugiesisch</string>
    <string name="privacy">Datenschutzerklärung</string>
    <string name="product_info">Produktinformation</string>
    <string name="pwd">Passwort</string>
    <string name="pwd_have_modified">Passwort geändert</string>
    <string name="pwd_hint">1) Ihr Passwort muss zwischen 8 und 20 Zeichen lang sein. 2) Ihr Passwort muss mindestens einen Grossbuchstaben oder einen Kleinbuchstaben enthalten. 3) Ihr Passwort muss mindestens eine Ziffer enthalten (z. B.: 0, 1, 2, 3 usw.)</string>
    <string name="pwd_modify_failed">Das alte Passwort ist falsch, Änderung fehlgeschlagen</string>
    <string name="pwd_modify_success_to_relogin">das Passwort wurde erfolgreich geändert</string>
    <string name="pwd_not_equal">Passwort und Bestätigungspasswort stimmen nicht überein.</string>
    <string name="pwdmodify">Passwort zurücksetzen</string>
    <string name="qs_feedback">Feedback senden</string>
    <string name="query_allinfo">Sendeanforderung für alle Geräteinformationen</string>
    <string name="query_currenttimeset">Eingestellte aktuelle Uhrzeit senden</string>
    <string name="query_inputpwd">Eingegebenes Passwort senden</string>
    <string name="query_languageset">Sendeanforderung für Spracheinstellungen des Geräts</string>
    <string name="query_machine_config">Gerätekonfiguration anfordern</string>
    <string name="query_machine_info">Sendeanforderung für Geräteinformationen</string>
    <string name="query_multiarea">Sendeanforderung für Multizonen-Einstellungen des Geräts</string>
    <string name="query_nameinfo">Sendeanforderung für Gerätenamen</string>
    <string name="query_notifyupdate">Software-Update-Benachrichtigung senden</string>
    <string name="query_pwdinfo">Sendeanforderung für Gerätepasswort</string>
    <string name="query_rainset">Sendeanforderung für Regenverzögerungs-Einstellungen des Geräts</string>
    <string name="query_resetmachine">Anforderung senden: Zurücksetzen der Maschine</string>
    <string name="query_resetpwd">Zurücksetzen des Passworts anfordern senden</string>
    <string name="query_scheduleinfo">Sendeanforderung für Einsatzplan</string>
    <string name="query_scheduleset">Eingestellten Zeitplan senden</string>
    <string name="query_setlanguage">Eingestellte Sprache senden</string>
    <string name="query_setmultiarea">Eingestellte Multizonen senden</string>
    <string name="query_setname">Eingestellten Gerätenamen senden</string>
    <string name="query_setpwd">Eingestelltes Passwort senden</string>
    <string name="query_setrain">Eingestellte Regenverzögerung senden</string>
    <string name="query_setwifipwd">Einstellungen für WLAN-SSID und Passwort senden</string>
    <string name="query_workstatusinfo">Sendeanforderung für Betriebsstatus des Geräts</string>
    <string name="query_workstatusset">Eingestellten Betriebsstatus senden</string>
    <string name="rain_help_tip">Wenn die Regenverzögerungsfunktion eingeschaltet ist, kehrt der Mäher automatisch zur Ladestation zurück und wartet darauf, dass der Regen nach einer Verzögerungszeit aufhört, um die Arbeit wieder aufzunehmen. Hier können Sie die Verzögerungszeit einstellen.</string>
    <string name="rain_set_success">Regenverzögerung erfolgreich eingestellt</string>
    <string name="rainset">Regenverzögerung</string>
    <string name="re_pay">Erneut bezahlen</string>
    <string name="refresh_header_failed">Aktualisierung fehlgeschlagen</string>
    <string name="refresh_header_finish">Aktualisiert</string>
    <string name="refresh_header_loading">Wird geladen</string>
    <string name="refresh_header_pulling">Loslassen Zum Aktualisieren</string>
    <string name="refresh_header_refreshing">Wird geladen</string>
    <string name="refresh_header_release">loslassen</string>
    <string name="refresh_header_secondary">Losslassen zum 2. Ebene</string>
    <string name="refresh_header_update">Zuletzt aktualisiert MM -dd HH:mm</string>
    <string name="refund_in_progress">Rückerstattung</string>
    <string name="refund_money">Rückerstattungsbetrag</string>
    <string name="refund_reason">Grund für die Rückerstattung</string>
    <string name="refund_result">Ergebnis erstatten</string>
    <string name="refund_result_update_time">Aktualisierungszeit des Rückerstattungsergebnisses</string>
    <string name="refund_success">Rückerstattung erfolgreich</string>
    <string name="refund_tip">Hinweis: Nach der Rückerstattung funktioniert das Tracking-Modul aufgrund des unzureichenden Datenvolumens möglicherweise nicht richtig.</string>
    <string name="register">Registrieren</string>
    <string name="register_fail">Registrierung fehlgeschlagen</string>
    <string name="register_success">Registrierung erfolgreich</string>
    <string name="repeat_to">Zeitplan wiederholen bis</string>
    <string name="replace">Austauschen</string>
    <string name="repurchase">Erneut kaufen</string>
    <string name="request_refund">Erstattungsantrag</string>
    <string name="request_refund_time">Zeit der Rückerstattungsanfrage</string>
    <string name="request_success">Anfrage erfolgreich</string>
    <string name="reset">Passwort zurücksetzen</string>
    <string name="reset_content">Wollen Sie das Gerätepasswort zurücksetzen?</string>
    <string name="reset_failed">Zurücksetzen fehlgeschlagen</string>
    <string name="reset_main_person_reset_pwd">Nur Hauptkonto kann Gerätepasswort zurücksetzen</string>
    <string name="reset_send_failed">Zurücksetzen-Befehl konnte nicht gesendet werden</string>
    <string name="reset_send_succeess">Zurücksetzen-Befehl gesendet</string>
    <string name="reset_succeess">Zurücksetzen erfolgreich</string>
    <string name="response_hint">Inhalt der Antwort</string>
    <string name="retry">Erneut versuchen</string>
    <string name="retry_again">Erneut anfordern</string>
    <string name="romanina">rumänisch</string>
    <string name="russian">Russland</string>
    <string name="saturday">Sa.</string>
    <string name="save">Speichern</string>
    <string name="save_success">Erfolgreich eingestellt</string>
    <string name="scan_hint">QR-Code innerhalb des Rahmens platzieren</string>
    <string name="scan_to_add_device">Einen QR-Code scannen, um Geräte zu verwenden</string>
    <string name="schedule">Zeitplan</string>
    <string name="search_menu_title">Suche</string>
    <string name="select_pay_method">Wählen Sie die Zahlungsmethode</string>
    <string name="send_code">senden</string>
    <string name="sending_cmd">Befehl senden</string>
    <string name="sensitivity">Empfindlichkeit</string>
    <string name="sensor_timeout">Zeitüberschreitung des Kollisionssensors</string>
    <string name="serbia">Serbien</string>
    <string name="server_connect_fail">Server connection failure</string>
    <string name="service_msg_notification">Push-Benachrichtigung – Ankündigung</string>
    <string name="set_device_help">Grundlegende Informationen des Roboters</string>
    <string name="set_device_wifi">Einstellung des mit dem Roboter verbundene WLAN-Netzwerks</string>
    <string name="set_devicename">Name des Geräts</string>
    <string name="set_go_help">Stellen Sie die Position ein, an der der Roboter entlang der Grenze zu arbeiten beginnt, damit er problemlos verschiedene Bereiche abdecken kann</string>
    <string name="set_go_help1">Stellen Sie die Position ein, an der der Roboter entlang der Grenze zu arbeiten beginnt, damit er problemlos verschiedene Bereiche abdecken kann.Durch Bearbeiten der Häufigkeit können Sie die Häufigkeit der jeden Startpunkte ändern</string>
    <string name="set_led_fail">Scheinwerfereinstellung fehlgeschlagen</string>
    <string name="set_led_success">Scheinwerfereinstellung erfolgreich</string>
    <string name="set_mode_error">Befehlsausführung fehlgeschlagen</string>
    <string name="set_mode_success">Befehl ausgeführt</string>
    <string name="set_rain_help">Sie können den Regensensor ein-/ausschalten. Regenverzögerung bedeutet, dass der Mäher, nachdem er Regen erkannt hat, eine festgelegte Zeit verzögert (nachdem der Regensensor trocken ist), bevor er mit der Arbeit beginnt</string>
    <string name="set_schedule_failed">Einrichtung fehlgeschlagen</string>
    <string name="set_schedule_success">Zeitplan erfolgreich eingestellt</string>
    <string name="set_success">Erfolgreich eingestellt</string>
    <string name="set_ultra_fail">Ultraschalleinrichtung fehlgeschlagen</string>
    <string name="set_ultra_success">Ultraschalleinrichtung erfolgreich</string>
    <string name="setrain_error">Einrichtung fehlgeschlagen</string>
    <string name="setrain_success">Regenverzögerung erfolgreich eingestellt</string>
    <string name="setting">Einstellungen</string>
    <string name="sex">Geschlecht</string>
    <string name="share_device">Teilen</string>
    <string name="share_failed">Teilen fehlgeschlagen</string>
    <string name="slanting_bar">|</string>
    <string name="sloop_steep">Hang zu steil</string>
    <string name="slovak">slowakisch</string>
    <string name="slovenisch">Slowenisch</string>
    <string name="sn_not_legal">SN ungültig</string>
    <string name="spanish">Spanisch</string>
    <string name="star_devicename">Name des Geräts</string>
    <string name="star_feedbacktype">Feedback-Typ</string>
    <string name="star_name">*Name</string>
    <string name="start_edge_cutting">Kantenschneiden starten</string>
    <string name="start_point">Startpunkt</string>
    <string name="start_point_close_tip">Die Startpunktfunktion ist ausgeschaltet. Sie können es unter Einstellungen - Startpunkt aktivieren.</string>
    <string name="start_point_set">Startpunkt</string>
    <string name="start_time">Startzeit</string>
    <string name="start_time_one">Startzeit 1</string>
    <string name="start_time_two">Startzeit 2</string>
    <string name="status_bar_notification_info_overflow">999+</string>
    <string name="stop">Stopp</string>
    <string name="stop_share_failed">Teilen kann nicht gestoppt werden</string>
    <string name="stop_share_success">Teilen gestoppt</string>
    <string name="stop_share_tip">Nachdem Sie die Freigabe beendet haben, können andere Ihre Geräte nicht mehr verwenden.</string>
    <string name="submit">Abschicken</string>
    <string name="submit_application">Anfrage einreichen</string>
    <string name="submitted_application">Anfrage eingereicht</string>
    <string name="suggest_use_wifi">Das Bluetooth-Upgrade dauert lange. Es wird empfohlen, zum Upgrade eine Verbindung zu WLAN herzustellen</string>
    <string name="sunday">So.</string>
    <string name="sure_to_delete_the_device">Bestätigen, um Gerät zu löschen</string>
    <string name="sweden">Schwedisch</string>
    <string name="take_picture">Foto aufnehmen</string>
    <string name="the_day_after">nächster Tag</string>
    <string name="the_day_before">vorheriger Tag</string>
    <string name="thursday">Do.</string>
    <string name="time_set">Zeiteinstellungen</string>
    <string name="time_sync">Zeitkalibrierung</string>
    <string name="time_zone">Zeitzone</string>
    <string name="time_zone_tip">Uhrzeit mit Internetzeit synchronisieren</string>
    <string name="timeout_along_line">Zeitüberschreitung entlang der Begrenzungslinie</string>
    <string name="timeset_error">Fehler bei der Zeiteinstellung</string>
    <string name="to_charge">Aufladen</string>
    <string name="to_fill">Jetzt ausfüllen</string>
    <string name="track_alert_bind">Tracking-Modul verbinden</string>
    <string name="tracking_alerts_notification">Push-Benachrichtigung – Tracking-Alarm</string>
    <string name="tracking_alerts_push">Tracking-Warnmeldungen</string>
    <string name="traffic_recharge">Datenvolumen aufladen</string>
    <string name="trapped">Sitzt fest</string>
    <string name="try_reopen_ble">Bitte Bluetooth einschalten</string>
    <string name="tuesday">Di.</string>
    <string name="ultra_tip">Sie können die Ultraschall-Hinderniserkennung ein-/ausschalten und den Abstand für die Ultraschallerkennung von Hindernissen einstellen</string>
    <string name="ultrasonic_sensor_error">Leiterplattenfehler des Ultraschallsensors</string>
    <string name="ultrasonic_setting">Ultraschalleinstellungen</string>
    <string name="unbind_tip">Nachdem das Ortungsmodul von Ihrem Gerät entfernt wurde, kann es den Rasenmäher nicht mehr orten. Möchten Sie es wirklich entfernen?</string>
    <string name="update_content">Inhalt aktualisieren</string>
    <string name="update_help">Aktualisierung der Firmware des Roborasenmähers</string>
    <string name="update_version">letzte Version</string>
    <string name="updown">Auf/ab</string>
    <string name="usage">Bedienungsanleitung</string>
    <string name="user_content">\t\t\t\tSHANGHAI SUNSEEKER ROBOTIC TECHNOLOGY CO.,LTD. provides you with  SUNSEEKER  robotic lawn mower intelligent service application products. This software is a service mobile application software based on  SUNSEEKER  robotic lawn mower. Please read each clause in this agreement carefully. \n\n\t\t\t\tPlease read and understand all the rights and restrictions stipulated in the User Agreement (hereinafter referred to as the Agreement) before using the  SUNSEEKER  lawn mower series products (hereinafter referred to as this product), especially the bold part of the font. If you have any questions about the content of this agreement or the information on the page, please do not proceed to the next step. \n\n\t\t\t\tSHANGHAI SUNSEEKER ROBOTIC TECHNOLOGY CO.,LTD. (hereinafter referred to as  SUNSEEKER) respects and will strictly protect the legitimate rights and interests of users (including user privacy, user data, etc.) when using this product from any infringement. \n\n\t\t\t\tThis agreement will be legally binding on the user\'s use of this product, and you have promised and guaranteed that you have the right and ability to enter into this agreement. If you are a person with no capacity for civil conduct or a person with limited capacity for civil conduct, please inform your guardian, and read this agreement and use our services under the guidance of your guardian. Users who start to use this product will be deemed to have accepted this agreement and are voluntarily bound by this agreement. Please carefully read and understand the terms of this agreement, especially the exemption clauses exempting and restricting SUNSEEKER’s liability and the user\'s rights restrictions (minors should be accompanied by legal guardians when reviewing), if you cannot accept all terms in this agreement, please do not use this product. Your download, installation, use of this software or account acquisition or login will be deemed as acceptance of this agreement, and you agree to be bound by the terms of this agreement. \n\n\t\t\t\tSUNSEEKER ROBOTIC has the right to amend this agreement, and the updated terms of the agreement will be published in this product, effective from the date of publication. After SUNSEEKER ROBOTIC modifies the terms of this agreement, if the user does not accept the modified terms, please stop using the product immediately, and the user will be deemed to have accepted the modified agreement if the user continues to use the product. \n\n1、Registration and confirmation \n\n1.1 If you install and use this product, you must register and provide relevant personal information on the registration page. Once you register or use this service, you are deemed to have fully understood and agreed to all the terms under this agreement, including any modifications made by SUNSEEKER ROBOTIC to this agreement. At the same time you must promise and guarantee: \n\n1.1.1 All registration information you submit must be true and accurate; \n\n1.1.2 Your use of this product must be legal; \n\n1.1.3 You can terminate the use of your account at any time by instructions; \n\n1.1.4 Be sure to read carefully and fully understand the content of each clause. If you do not agree with this statement or any of its content, you should immediately stop the registration process. \n\n1.2 Be sure to read carefully and fully understand the content of each clause. If you do not agree with this statement or any of its content, you should immediately stop the registration process. \n\n1.2.1 After you agree to this agreement and the Privacy Policy or register, you are deemed to agree that this product can obtain your information, data, etc., and agree that this product will integrate and use your information and data under the premise of compliance with laws and regulations, in order to provide you with better various service functions or continuous services, create service value by maximizing the use of your data. Please read it carefully during registration. After obtaining your consent, this product will collect subsequent information. This product guarantees that it will not collect information that is prohibited by laws and regulations. Information collected includes: \n\n1.2.2 When you register as a member, the email address provided is used to help you automatically extract information such as changes to the account binding or managed smart devices; \n\n1.2.3 The information proactively provided to us when you browse or use SUNSEEKER ROBOTIC \'s products or services can help you quickly get after-sales service and devices details management. We can use the information you provide to profile your behavior preferences, etc., so as to provide you with more personalized and convenient services; \n\n1.2.4 Relevant information recorded in the process of providing you with services, so that you can check the required devices dynamics or related after-sales service progress, etc.; \n\n1.2.5 When providing after-sales service to you, we will collect your location information and devices status for perfect service, so as to provide you with more perfect and faster service; \n\n1.2.5 You can actively submit feedback information through our customer service staff or other channels, so that we can understand and evaluate service quality and optimize user experience; \n\n1.2.6 Collect and store legally obtained information about you from affiliates, business partners, or third-party independent sources; \n\n1.2.7 The information you provide,  SUNSEEKER ROBOTIC  will maximize the reasonable business obligations to keep confidential. With your consent, this product will provide you with services such as the information of device’s after-sales service and version upgrades. \n\n1.3 Your other information \n\nIn order to make it more convenient for you to use this product and improve the security of your use of our services, our server will collect Mac information about your lawn mower device, Bluetooth information that can be obtained by mobile terminals, device location information, third-party account user\'s name, profile picture and other similar characteristics records. \n\n2、 User content \n\n2.1 User content refers to all content generated when the user downloads, publishes or uses this product in other ways (for example: your information, pictures or other content); \n\n2.2 You are the only person responsible for your user content. After you register, operations and instructions due to your user content are deemed to be made by you. If the account, password and other information is fraudulently used, stolen or used illegally due to your reasons, you shall bear the risks and losses caused by this. At the same time, you will bear the risk of you or any third party being identified due to the disclosure of your user content; \n\n2.3 You have agreed that your user content is restricted by Article 4; \n\n2.4 According to the provisions of this agreement, this product will grant you the following non-transferable, non-exclusive licenses: \n\n2.4.1 Right to use this product; \n\n2.4.2 The right to download, install, and use this product in all your network communications. \n\n2.5 Based on the needs of operational and safety, we may suspend or restrict some functions of the software service of this product, or add new functions \n\n3、 SUNSEEKER ROBOTIC owns all the rights, ownership and interests of this product, including related intellectual property rights. \n\n4、 Restrictive clause \n\n4.1 You cannot license, sell, lease, transfer, distribute or use this product in any form for other commercial purposes; \n\n4.2 Unless expressly provided by law, you cannot copy, distribute, republish, download, display or post any part of this product in any form or method; \n\n4.3 You have agreed to upload, publish or o use this product service in other ways. During the use, you will bear all legal responsibilities arising from the risks caused by the following actions: \n\n4.3.1 Undermining the basic principles established by the Constitution; \n\n4.3.2 Endangering national security, leaking state secrets, subverting state power, and undermining national unity \n\n4.3.3 Damaging the reputation or interests of the state; \n\n4.3.4 Inciting ethnic hatred or discrimination to undermine ethnic solidarity; \n\n4.3.5 Detrimental to state religious policies, propagating heretical or superstitious ideas; \n\n4.3.6 Spreading rumors to disturb economic and social order; \n\n4.3.7 Disseminating obscenity, pornography, force, brutality and terror or crime-abetting; \n\n4.3.8 Humiliating or defaming others or infringing upon their reputation, privacy and other legitimate rights and interests; \n\n4.3.9 Other contents as prohibited by laws and administrative regulations. \n\n4.4 You have agreed not to engage in the following behaviors with this product: \n\n4.4.1 Upload or publish computer viruses, worms, malicious code, software that deliberately destroys or changes computer systems or data; \n\n4.4.2 Collect information or data of other users without authorization, such as real names, ID numbers, and mobile phone numbers; \n\n4.4.3 Disable the client of this software, cause excessive burden on the server or interfere in other ways; \n\n4.4.4 Try to use or access this product or background server without authorization; \n\n4.4.5 Interfere with or destroy the use of other users of this product. \n\n5、 User privacy protection \n\n\t\t\t\t Privacy Policy is a part of this agreement, you can find it in the Privacy Policy on the previous interface. Please read carefully and understand all the content in the privacy policy. Your use of this product is deemed that you understand and agree to be bound by the privacy policy, otherwise, please do not use this product. \n\n6、 Modification and termination \n\n6.1 Modification \n\n6.1.1 This agreement allows for changes at any time. If there are any substantial changes to this agreement, we will notify you through the official website or announcement of this product. If you continue to use this product after this agreement has been changed, it will be deemed that you agree to be bound by the changed terms; \n\n6.1.2 SUNSEEKER ROBOTIC reserves the right to modify, reserve or close any service of this product at any time without notice; \n\n6.1.3 You have agreed that SUNSEEKER ROBOTIC does not need to be liable to you or a third party for modifying, retaining or closing any service of this product. \n\n6.2 Termination \n\n6.2.1 This agreement is effective from the date you accept it, and will continue to be effective during your use of this product until terminated in accordance with this agreement; \n\n6.2.2 Notwithstanding the above provisions, if you use this product earlier than the time you accept this agreement, you hereby know and agree that this agreement will take effect the first time you use this product; \n\n6.2.3 We may (1) reserve your right to use this product or account on this website in accordance with the provisions of the law; (2) we will terminate this agreement at any time and for any reason, regardless of whether you notify it or not, including the good faith belief that you violated our acceptable use policy or other provisions of this agreement; \n\n6.2.4 Not limited by the provisions of the preceding paragraph, if the user infringes the intellectual property rights or other legal rights of a third party, SUNSEEKER ROBOTIC reserves the right to terminate this agreement after receiving the notice from the right holder or its agent; \n\n6.2.5 Once this agreement is terminated, your right to use this product will terminate. You should be aware that the termination of your agreement means that your user content will be deleted from our active database. SUNSEEKER ROBOTIC shall not be liable to you for terminating this agreement, including but not limited to terminating your user account and deleting your user content. \n\n7、Third Party Information and Services \n\n7.1 You have known or agreed that our services are based on third-party technical support, such as Apple iOS, Google Android, etc. You already know that this agreement is signed between you and SUNSEEKER ROBOTIC, not between you and the aforementioned third party. SUNSEEKER ROBOTIC is the only person responsible for the content, maintenance, support services, guarantees and litigation arising from this product. You have agreed to comply with and authorize SUNSEEKER ROBOTIC to restrict your conditional use of this product\'s services; \n\n7.2 Such third party’s terms and policies shall apply to the User’s use of such third party information and services. \n\n7.3Your interaction with other users is only the behavior between you and other users, and this product does not assume any legal responsibility for such behavior. You have agreed that this product will not be liable for the results of such interactive behaviors. \n\n8、Notification \n\n8.1 The user must provide a valid email address that you frequently use recently in the account of this product. This product is not responsible for the risk that the email address you provided cannot be used or for any reason so that we cannot deliver the notice to you; \n\n8.2 The announcement notice issued by this product or the email containing such notice sent to you will undoubtedly constitute a valid notice. \n\n9、Applicable law \n\n9.1 This agreement is governed by the laws of the People\'s Republic of China \n\n9.2 If there is a dispute between the two parties, they should be resolved through friendly negotiation; if the negotiation fails, either party should file a lawsuit in the court where SUNSEEKER ROBOTIC is located. \n\n10、 Independence \n\n\t\t\t\tSome terms in this agreement cannot be applied for some reason, other terms of this agreement continue to apply and the unapplicable terms will be modified so that they can be applied in accordance with the law. \n\n11、Entire Agreement \n\n11.1 This Agreement, including the Privacy Policy, is the final, complete and exclusive agreement between you and this Product regarding matters related to this Product, and supersedes and incorporates any previous discussions and agreements between the Parties regarding such matters, including the previous end user authorization, service terms and privacy policy; \n\n11.2 The heading for each part is inserted for convenience of reading, and does not imply any legal or contractual obligations; \n\n11.3 Unless as approved by SUNSEEKER ROBOTIC in writing, you are not allowed to transfer any right or obligation provided in this Agreement. Any attempt of transfer in violation of above provisions shall be invalid. \n\n12、 Disclaimer \n\n\t\t\t\tIf the following situations occur, this product does not assume any legal liability in the event of any of the following: \n\n12.1 provision of your personal information as required by law or as required by relevant government agencies; \n\n12.2 disclosure of any personal information due to your own improper use or other reasons; \n\n12.3 Failure to satisfy Customers\' requirements caused by any interruption, blockage, etc. because of hacking, computer virus intrusion, illegal content information, harassment information screening, government control and monitor as well as problems with any other network, technology, communication lines, information security management measures, etc; \n\n12.4 The Customer\'s communication line failure caused by the third party such as the operator, technical problems, network, computer failure, system instability and other losses caused by force majeure; \n\n12.5 The risks associated with the use of this product’s information, procedures, and services that may have anonymous or impersonal information, including threatening, defamatory, offensive, or illegal content; \n\n12.6 Any psychological, physical, or economic losses caused by interactions with other customers and their deceiving or misleading information. \n\n13、 Contact information \n\n\t\t\t\tPlease contact us if you have any issues regarding our Privacy Policy and User Agreement, including questions on exercising your rights, any enquiries or complaints, opting-out of direct marketing information, or have any questions about the processing of your personal information, please contact us according to the following contact information. If your concerns are not resolved, you have the right to complain to your local authorities, workplace, or local regulatory agency, where you believe a violation occurred. \n\n\t\t\t\t Adress: Rm.301, 226 Gaoji Ra., SiJing Town, SongJiang District, Shanghai, China \n\n\t\t\t\tEmail: Harry@sunseekerpower.cn \n\n14、Effective date \n\n\t\t\t\tThe effective date of this Agreement is November 5, 2020.</string>
    <string name="user_set">Benutzereinstellungen</string>
    <string name="useragreement">Nutzungsvereinbarung</string>
    <string name="useragreement_privacypolicy">Nutzungsvereinbarung und Datenschutzerklärung</string>
    <string name="username_exist">Benutzername bereits vorhanden</string>
    <string name="username_not_exist">Benutzerinformationen konnten nicht abgerufen werden</string>
    <string name="video_to_large">Videos zu groß</string>
    <string name="view_order">Bestellung ansehen</string>
    <string name="wait_to_pay_tip">Bitte schließen Sie die Zahlung innerhalb von 30 Minuten ab, das System storniert die Bestellung automatisch nach Ablauf der Zeit.</string>
    <string name="warning_tip_180">Rückerstattungen können innerhalb von 180 Tagen basierend auf der Nutzungszeit vorgenommen werden. Keine Rückerstattung nach 180 Tagen.</string>
    <string name="wednesday">Mi.</string>
    <string name="welcome_to_use">Willkommen zur Nutzung der Mähroboter-APP.</string>
    <string name="well">Sehr gut</string>
    <string name="wheel_block">Radmotor blockiert</string>
    <string name="white_light">weißes Licht</string>
    <string name="wifi_connect">Mit WLAN verbinden</string>
    <string name="wifi_connect_reset_config">Gerät ist derzeit online, Sie können Ihre Netzwerkinformationen eingeben und neu konfigurieren</string>
    <string name="wifi_matching">Aufbau der Verbindung, bitte warten</string>
    <string name="wifi_set">WLAN-Einstellungen</string>
    <string name="wifi_tips">Tipps: Bitte prüfen Sie, ob ein WLAN-Signal vorhanden ist.\nBitte verbinden Sie die Geräte an einem Ort mit starkem WLAN-Signal. \nBitte prüfen Sie, ob das WLAN 2,4 GHz verwendet.</string>
    <string name="woman">Weiblich</string>
    <string name="work">Betrieb</string>
    <string name="work_area_exceeds_set_value">Überschreitet den eingestellten Arbeitsbereich</string>
    <string name="work_map_tip">1. Karte wird während der Arbeit generiert und optimiert. 2. Startpunkte können direkt auf der Karte angepasst werden.</string>
    <string name="work_plan">Zeitplan</string>
    <string name="work_tips">Der Mähroboter kann nur per App gestartet werden, wenn er in der Ladestation steht.</string>
    <string name="working">Betrieb</string>
    <string name="xiubian_help_tips">Wenn Sie an diesem Tag „Kante“ auswählen, schneidet die Maschine entlang der Begrenzung, wenn sie an diesem Tag automatisch zum ersten Mal mit der Arbeit beginnt</string>
    <string name="zone1">Startpunkt 1</string>
    <string name="zone2">Startpunkt 2</string>
    <string name="zone3">Startpunkt 3</string>
    <string name="zone4">Startpunkt 4</string>
</resources>